<text xmlns="http://www.tei-c.org/ns/1.0"><body><pb facs="#img_237"/>
<ab>
<metamark facs="#img_237-0001" place="margin(top) margin(left)" function="folio" change="#StDa" rend="no-caret _Cg">60</metamark>
<metamark facs="#img_237-0003" place="margin(top) margin(right)" function="folio" change="#StEb" rend="no-caret _HMp">107</metamark>
  <metamark facs="#img_237-0002" place="margin(top) margin(right)" function="folio" rend="no-caret _HMp"><add facs="#img_237-0002" rend="bubble _HMp" place="above" hand="#RW">85</add></metamark>
<metamark facs="#img_237-0005" place="margin(bottom) margin(left)" function="folio" rend="no-caret _HMp">96</metamark>
any able-bodied <subst facs="#img_237-0006"><del facs="#img_237-0006" rend="overwritten _ink1" type="superimposed" hand="#HM"><hi rend="underline">suspect</hi></del><add facs="#img_237-0006" rend="superimposed _HMp" type="superimposed" hand="#HM" change="#StDa">suspect</add></subst><add facs="#img_237-0009" rend="no-caret" place="inline" hand="#HMp" change="#StDa">,</add> <del facs="#img_237-0007" rend="single-stroke" hand="#HMp" change="#StDa">and</del> <add facs="#img_237-0008" rend="no-caret" place="inline" hand="#HMp" change="#StDa">any</add>
  <lb/>questionable <subst facs="#img_237-0010"><del facs="#img_237-0010" rend="overwritten _ink1" type="superimposed" hand="#HM">fellows</del><add facs="#img_237-0010" rend="superimposed _HMp" type="superimposed" hand="#HM" change="#StDa">fellow</add></subst> at large and <metamark facs="#img_237-0004" place="inline" function="composition-information" change="#StEb" rend="no-caret _HMp"><add facs="#img_237-0004" rend="bubble _HMp" place="inline" hand="#HM" change="#StEb">s</add></metamark>
  <lb/>summarily ship <del facs="#img_237-0013" rend="single-stroke _HMp" hand="#HM" change="#StDa">them</del> <metamark facs="#img_237-0011" place="inline" function="caret" change="#StDa" rend="caret _HMp">^</metamark> <add facs="#img_237-0012" rend="caret _HMp" place="above" hand="#HM" change="#StDa">him</add> to the dock-yard
  <lb/>or fleet.  Furthermore, even among
  <lb/>voluntary enlistments there were
  <lb/>instances where the motive <del facs="#img_237-0014" rend="single-stroke _ink1" hand="#HM" change="#StDa">to it</del>
  <lb/>thereto partook neither of patriotic
  <lb/>impulse nor yet of a random
  <lb/>desire to experice a bit of sea-life
  <lb/>and martial adventure.  Insolvent
  <lb/>debtors of <del facs="#img_237-0015" rend="multi-stroke _HMp" hand="#HM" change="#StDa">the</del> minor grade, together
  <lb/>with the promiscuous lame ducks
  <lb/>of morality found in the Navy
  <lb/>a convenient and secure refuge.
  <lb/>Secure, because once enlisted
  <lb/>aboard a King's-Ship, they <add facs="#img_237-0016" rend="no-caret _ink1" place="inline" hand="#HM" change="#StEb">were as</add>
  <lb/><add facs="#img_237-0017" rend="no-caret _ink1" place="inline" hand="#HM" change="#StEb">much</add> <del facs="#img_237-0018" rend="single-stroke _ink1" hand="#HM" change="#StEb">were</del> in sanctuary, as <del facs="#img_237-0019" rend="single-stroke _ink1" hand="#HM" change="#StEb">it were.</del>
  <add facs="#img_237-0022" rend="no-caret _ink1" place="inline" hand="#HM" change="#StEb"><lb/>the transgressor of the Middle Ages harboring himself
  <lb/>under the shadow of the altar.</add>
</ab></body></text>