<text xmlns="http://www.tei-c.org/ns/1.0"><body><div><pb facs="#img_181"/>
<ab>
<metamark facs="#img_181_z001" place="margin(top) margin(left)" function="folio" rend="no-caret _HMp">53</metamark>
<metamark facs="#img_181_z005" place="margin(top) margin(right)" function="folio" rend="no-caret _HMp"><add facs="#img_181_z005" rend="bubble" place="above" hand="#RW">64</add></metamark>
<metamark facs="#img_181_z006" place="margin(top) margin(right)" function="folio" change="#StEb" rend="no-caret _Cr">95 </metamark>
<metamark facs="#img_181_z007" place="margin(top) margin(right)" function="folio" change="#StEc" rend="#no-caret _Cr"><add facs="#img_181_z007" rend="no-caret _Cr" place="below" hand="#HM" change="#StEc"><hi rend="bubble">1</hi></add></metamark>
<metamark facs="#img_181_z016" place="margin(bottom) margin(left)" function="folio" rend="no-caret _HMp">77</metamark>
guest, a civilian aboard the King's-ship
  <lb/>some highly honorable discreet envoy
  <lb/>on his way to an important post.
  <lb/>But in fact this unobtrusivness of
  <lb/>demeanor <metamark facs="#img_181_z008" place="inline" function="caret" change="#StEc" rend="no-caret _ink1">^ </metamark><add facs="#img_181_z010" rend="caret _ink1" place="above" hand="#HM" change="#StEc">may have</add> proceeded from a certain
  <lb/>unaffected modesty of manhood <add facs="#img_181_z012" rend="no-caret _ink1" place="inline" hand="#HM" change="#StEc">sometimes</add>
  <lb/>accompanying a resolute nature, a
  <lb/>modesty evinced at all times not
  <lb/>calling for pronounced action, and
  <lb/>which shown in any rank of life
  <lb/>suggests a virtue aristocratic in kind.<metamark facs="#img_181_z013" place="below" function="insertion-device" change="#StEc" rend="no-caret _HMp">\\</metamark>
</ab>
</div></body></text>