<text xmlns="http://www.tei-c.org/ns/1.0"><body><div><pb facs="#img_687"/>
<ab>
  <metamark place="margin(top) margin(right)" function="folio" rend="no-caret _HMp" change="StFa" facs="#img_687_z001">286</metamark> <!-- add @hand="#RW" later -->
  <metamark place="margin(bottom) margin(left)" function="folio" rend="no-caret _HMp" change="StFa" facs="#img_687_z018">297</metamark> <!-- add @hand="#HT" later -->
  ordinary routine preliminary to the
  <lb/>end. <del rend="single-stroke _HMp" hand="#HM" change="StFa" facs="#img_687_z021">Put in irons, he was consigned</del> <add place="above" rend="no-caret _HMp" hand="#HM" change="StFa" facs="#img_687_z003">His transfer <metamark place="inline" function="caret" rend="caret _HMp" change="StFa" facs="#img_687_z032">^</metamark><!-- hand="#HM" --><add place="below" rend="caret _HMp" hand="#HM" change="StFa" facs="#img_687_z004">under guard</add> from the Captain's quarters</add>
  <lb/><del rend="multi-stroke _HMp" hand="#HM" change="StFa" facs="#img_687_z022">to <add place="above" rend="no-caret _HMp" hand="#HM" change="StFa" facs="#img_687_z005">to</add> the customary place set apart in</del>
  <lb/><metamark place="inline" function="caret" rend="caret _HMp" change="StFa" facs="#img_687_z037">^</metamark><!-- hand="#HM" --><del hand="#HM" change="StFa" facs="#img_687_z009"><add place="above" rend="caret _HMp" hand="#HM" change="StFa" facs="#img_687_z009">great</add></del> <del rend="multi-stroke _HMp" hand="#HM" change="StFa" facs="#img_687_z023">war-ships for the safe-keeping of</del>
  <lb/><del rend="multi-stroke _HMp" hand="#HM" change="StFa" facs="#img_687_z034">prisoners previous to punishment.</del> <del rend="multi-stroke _ink1" hand="#HM" change="StFa" facs="#img_687_z035">In</del>
  <lb/><del rend="single-stroke _HMp" hand="#HM" change="StFa" facs="#img_687_z020">This</del> <del rend="single-stroke _HMp" hand="#HM" change="StFa" facs="#img_687_z006"><add place="above" rend="no-caret _HMp" hand="#HM" change="StFa" facs="#img_687_z006">tho' <app><rdg resp="MEL">n</rdg><rdg resp="HS">m</rdg></app></add></del> was effected without <del rend="single-stroke _HMp" hand="#HM" change="StFa" facs="#img_687_z025">any</del> <add place="inline" rend="no-caret _HMp" hand="#HM" change="StFa" facs="#img_687_z039">unusual</add>
  <lb/>precautions–at least <restore change="StFa" hand="#HM" facs="#img_687_z011"><hi rend="restoration">no</hi></restore> <del rend="single-stroke _HMp" hand="#HM" change="StFa" facs="#img_687_z010"><add place="above" rend="no-caret _ink1" hand="#HM" change="StFa" facs="#img_687_z010">few</add></del> visible ones<subst facs="#img_687_z040"><del rend="overwritten _ink1" hand="#HM" change="StFa" facs="#img_687_z040">––</del><add place="inline" rend="overwritten _ink1" hand="#HM" change="StFa" facs="#img_687_z040">.</add></subst> <!-- not sure if this is right, but it seems he initially wanted to stop the sentence, then added more? -->
  <lb/><metamark place="inline" function="folio" rend="no-caret _HMp" change="StFa" facs="#img_687_z013">61</metamark><metamark place="below" function="folio" rend="bubble _HMp" change="StFa" facs="#img_687_z014"><hi rend="bubble">1</hi></metamark><!-- hand="#HM" -->  <!-- hand="#HM" -->  <del rend="single-stroke _HMp" hand="#HM" change="StFa" facs="#img_687_z041">other than those usual in similar cases,</del> <del rend="single-stroke _HMp" hand="#HM" change="StFa" facs="#img_687_z012"><add place="above" rend="no-caret _HMp" hand="#HM" change="StFa" facs="#img_687_z012">every-day example</add></del> <del rend="single-stroke _HMp" hand="#HM" change="StFa" facs="#img_687_z015"><add place="below" rend="no-caret _HMp" hand="#HM" change="StFa" facs="#img_687_z015">of minor offenses.</add></del>
  <lb/>If possible not to let the men so
  <lb/>much as surmise that their officers
  <lb/>anticipate aught amiss from them
  <lb/>is the tacit rule<del rend="multi-stroke _ink1" hand="#HM" change="StFa" facs="#img_687_z029">,</del> in a military ship.
  <lb/>And the more that some sort of
  <lb/>trouble should really be apprehended
  <lb/>the more do the officers keep that
  <lb/>apprehension to themselves; tho' not the
  <lb/>less unostentatious <metamark place="inline" function="caret" rend="caret _ink1" change="StFa" facs="#img_687_z031">^</metamark><!-- hand="#HM" --><add place="below" rend="caret _ink1" hand="#HM" change="StFa" facs="#img_687_z017">vigilance</add> may be augmented.
  <lb/><del rend="erasure _HMp" hand="#HM" change="StFa" facs="#img_687_z030"><metamark place="margin(bottom)" function="composition-information" rend="no-caret _HMp" change="StFa" facs="#img_687_z030">==//==</metamark><!-- hand="#HM" --></del>
</ab><milestone n="23" unit="chapter"/></div></body></text>